buildbot_wsgi_dashboards/VERSION
buildbot_wsgi_dashboards/__init__.py
buildbot_wsgi_dashboards/static/scripts.js
buildbot_wsgi_dashboards-4.3.0.dist-info/METADATA
buildbot_wsgi_dashboards-4.3.0.dist-info/WHEEL
buildbot_wsgi_dashboards-4.3.0.dist-info/entry_points.txt
buildbot_wsgi_dashboards-4.3.0.dist-info/top_level.txt
buildbot_wsgi_dashboards-4.3.0.dist-info/RECORD
