Metadata-Version: 2.1
Name: buildbot-wsgi-dashboards
Version: 4.3.0
Summary: Buildbot plugin to integrate flask or bottle dashboards to buildbot UI (React)
Home-page: http://buildbot.net/
Author: Buildbot maintainers
Author-email: devel@buildbot.net
Classifier: License :: OSI Approved :: GNU General Public License v2 (GPLv2)
